{
    "report_generated_time": "2025-09-09 14:55:58",
    "scan_directory": "..\\Wechat-Backup\\文不加点的张衔瑜",
    "articles": [
        {
            "path": "2025\\2025-08-18_夏天热冬天冷",
            "end_time": "2025-08-26 11:37:18",
            "size_bytes": 4179755,
            "size_mb": 3.99,
            "duration_from_previous_seconds": 0
        },
        {
            "path": "2025\\2025-08-09_自来水泵",
            "end_time": "2025-08-26 11:37:42",
            "size_bytes": 742956,
            "size_mb": 0.71,
            "duration_from_previous_seconds": 24.63
        },
        {
            "path": "2025\\2025-07-31_文不加点的张衔瑜八岁了",
            "end_time": "2025-08-26 11:38:00",
            "size_bytes": 388461,
            "size_mb": 0.37,
            "duration_from_previous_seconds": 17.8
        },
        {
            "path": "2025\\2025-07-28_Perplexity 困惑度",
            "end_time": "2025-08-26 11:38:24",
            "size_bytes": 1064053,
            "size_mb": 1.01,
            "duration_from_previous_seconds": 24.39
        },
        {
            "path": "2025\\2025-07-22_在天垂形",
            "end_time": "2025-08-26 11:39:29",
            "size_bytes": 6909442,
            "size_mb": 6.59,
            "duration_from_previous_seconds": 64.96
        },
        {
            "path": "2025\\2025-07-14_垂",
            "end_time": "2025-08-26 11:40:07",
            "size_bytes": 3196836,
            "size_mb": 3.05,
            "duration_from_previous_seconds": 37.62
        },
        {
            "path": "2025\\2025-07-06_這下好了，是這下壞了",
            "end_time": "2025-08-26 11:40:33",
            "size_bytes": 1381217,
            "size_mb": 1.32,
            "duration_from_previous_seconds": 26.31
        },
        {
            "path": "2025\\2025-07-02_歪嘴巴锅",
            "end_time": "2025-08-26 11:41:08",
            "size_bytes": 3873556,
            "size_mb": 3.69,
            "duration_from_previous_seconds": 34.99
        },
        {
            "path": "2025\\2025-06-24_语言光滑",
            "end_time": "2025-08-26 11:41:44",
            "size_bytes": 2851537,
            "size_mb": 2.72,
            "duration_from_previous_seconds": 35.3
        },
        {
            "path": "2025\\2025-06-17_让位",
            "end_time": "2025-08-26 11:42:43",
            "size_bytes": 6396991,
            "size_mb": 6.1,
            "duration_from_previous_seconds": 59.16
        },
        {
            "path": "2025\\2025-06-10_吃禽不是嘴过",
            "end_time": "2025-08-26 11:43:59",
            "size_bytes": 7072691,
            "size_mb": 6.75,
            "duration_from_previous_seconds": 76.24
        },
        {
            "path": "2025\\2025-06-02_量体裁衣",
            "end_time": "2025-08-26 11:44:29",
            "size_bytes": 1935982,
            "size_mb": 1.85,
            "duration_from_previous_seconds": 30.41
        },
        {
            "path": "2025\\2025-05-26_放空",
            "end_time": "2025-08-26 11:45:05",
            "size_bytes": 3064097,
            "size_mb": 2.92,
            "duration_from_previous_seconds": 35.56
        },
        {
            "path": "2025\\2025-05-15_留下尬走的足迹｜昆明楚雄遵义三峡",
            "end_time": "2025-08-26 11:47:49",
            "size_bytes": 25887851,
            "size_mb": 24.69,
            "duration_from_previous_seconds": 164.27
        },
        {
            "path": "2025\\2025-05-08_状况外",
            "end_time": "2025-08-26 11:48:17",
            "size_bytes": 2612285,
            "size_mb": 2.49,
            "duration_from_previous_seconds": 27.48
        },
        {
            "path": "2025\\2025-04-28_重在掺和",
            "end_time": "2025-08-26 11:48:39",
            "size_bytes": 698652,
            "size_mb": 0.67,
            "duration_from_previous_seconds": 22.57
        },
        {
            "path": "2025\\2025-04-20_检票员",
            "end_time": "2025-08-26 11:49:00",
            "size_bytes": 349144,
            "size_mb": 0.33,
            "duration_from_previous_seconds": 20.99
        },
        {
            "path": "2025\\2025-04-14_预制菜",
            "end_time": "2025-08-26 11:49:18",
            "size_bytes": 676672,
            "size_mb": 0.65,
            "duration_from_previous_seconds": 17.37
        },
        {
            "path": "2025\\2025-04-07_明亮",
            "end_time": "2025-08-26 11:49:43",
            "size_bytes": 1650562,
            "size_mb": 1.57,
            "duration_from_previous_seconds": 25.73
        },
        {
            "path": "2025\\2025-04-01_热了冷，冷了热",
            "end_time": "2025-08-26 11:50:13",
            "size_bytes": 5298670,
            "size_mb": 5.05,
            "duration_from_previous_seconds": 29.37
        },
        {
            "path": "2025\\2025-03-24_小雷音",
            "end_time": "2025-08-26 11:50:59",
            "size_bytes": 1125655,
            "size_mb": 1.07,
            "duration_from_previous_seconds": 45.87
        },
        {
            "path": "2025\\2025-03-18_变化快",
            "end_time": "2025-08-26 11:51:19",
            "size_bytes": 939776,
            "size_mb": 0.9,
            "duration_from_previous_seconds": 20.17
        },
        {
            "path": "2025\\2025-03-10_出入是门",
            "end_time": "2025-08-26 11:51:52",
            "size_bytes": 2303740,
            "size_mb": 2.2,
            "duration_from_previous_seconds": 33.48
        },
        {
            "path": "2025\\2025-03-03_认知武器",
            "end_time": "2025-08-26 11:52:17",
            "size_bytes": 1202922,
            "size_mb": 1.15,
            "duration_from_previous_seconds": 24.72
        },
        {
            "path": "2025\\2025-02-23_大气层没有居民",
            "end_time": "2025-08-26 11:52:32",
            "size_bytes": 125330,
            "size_mb": 0.12,
            "duration_from_previous_seconds": 15.58
        },
        {
            "path": "2025\\2025-02-16_晒太阳是被太阳晒",
            "end_time": "2025-08-26 11:52:55",
            "size_bytes": 785135,
            "size_mb": 0.75,
            "duration_from_previous_seconds": 22.12
        },
        {
            "path": "2025\\2025-02-09_高功耗",
            "end_time": "2025-08-26 11:53:14",
            "size_bytes": 1483226,
            "size_mb": 1.41,
            "duration_from_previous_seconds": 19.6
        },
        {
            "path": "2025\\2025-01-28_听风",
            "end_time": "2025-08-26 11:53:40",
            "size_bytes": 2790420,
            "size_mb": 2.66,
            "duration_from_previous_seconds": 26.24
        },
        {
            "path": "2025\\2025-01-18_躺在与这个社会不痛不痒",
            "end_time": "2025-08-26 11:54:17",
            "size_bytes": 3212842,
            "size_mb": 3.06,
            "duration_from_previous_seconds": 36.21
        },
        {
            "path": "2024\\2024-12-31_你更喜欢片面地醒着_100图和衔瑜的2024再见",
            "end_time": "2025-08-26 11:56:13",
            "size_bytes": 40481617,
            "size_mb": 38.61,
            "duration_from_previous_seconds": 116.51
        },
        {
            "path": "2024\\2024-12-26_留下尬走的足迹｜泉州",
            "end_time": "2025-08-26 11:57:40",
            "size_bytes": 6683302,
            "size_mb": 6.37,
            "duration_from_previous_seconds": 86.71
        },
        {
            "path": "2024\\2024-12-25_留下尬走的足迹｜曼谷、大城府",
            "end_time": "2025-08-26 12:02:48",
            "size_bytes": 85005269,
            "size_mb": 81.07,
            "duration_from_previous_seconds": 307.98
        },
        {
            "path": "2024\\2024-12-24_留下尬走的足迹｜巴厘岛爪哇岛",
            "end_time": "2025-08-26 12:08:49",
            "size_bytes": 86609497,
            "size_mb": 82.6,
            "duration_from_previous_seconds": 361.61
        },
        {
            "path": "2024\\2024-12-24_留下尬走的足迹｜柬埔寨",
            "end_time": "2025-08-26 12:12:35",
            "size_bytes": 66534674,
            "size_mb": 63.45,
            "duration_from_previous_seconds": 225.43
        },
        {
            "path": "2024\\2024-11-27_留下尬走的足迹｜巴淡岛",
            "end_time": "2025-08-26 12:14:15",
            "size_bytes": 12124051,
            "size_mb": 11.56,
            "duration_from_previous_seconds": 100.05
        },
        {
            "path": "2024\\2024-11-13_备忘录空空",
            "end_time": "2025-08-26 12:14:55",
            "size_bytes": 880811,
            "size_mb": 0.84,
            "duration_from_previous_seconds": 39.62
        },
        {
            "path": "2024\\2024-11-05_一本糊涂账",
            "end_time": "2025-08-26 12:15:12",
            "size_bytes": 120567,
            "size_mb": 0.11,
            "duration_from_previous_seconds": 17.83
        },
        {
            "path": "2024\\2024-11-02_则其负大舟也无力",
            "end_time": "2025-08-26 12:15:34",
            "size_bytes": 878359,
            "size_mb": 0.84,
            "duration_from_previous_seconds": 21.91
        },
        {
            "path": "2024\\2024-10-29_留下尬走的足迹｜京津",
            "end_time": "2025-08-26 12:17:07",
            "size_bytes": 8325806,
            "size_mb": 7.94,
            "duration_from_previous_seconds": 92.67
        },
        {
            "path": "2024\\2024-10-17_溨雨",
            "end_time": "2025-08-26 12:17:44",
            "size_bytes": 3134547,
            "size_mb": 2.99,
            "duration_from_previous_seconds": 36.98
        },
        {
            "path": "2024\\2024-10-09_火柴盒",
            "end_time": "2025-08-26 12:18:51",
            "size_bytes": 3614365,
            "size_mb": 3.45,
            "duration_from_previous_seconds": 66.61
        },
        {
            "path": "2024\\2024-09-30_太阳无非一颗晨星",
            "end_time": "2025-08-26 12:19:11",
            "size_bytes": 753086,
            "size_mb": 0.72,
            "duration_from_previous_seconds": 20.44
        },
        {
            "path": "2024\\2024-09-26_在庙里住了一天",
            "end_time": "2025-08-26 12:19:53",
            "size_bytes": 3306193,
            "size_mb": 3.15,
            "duration_from_previous_seconds": 42.39
        },
        {
            "path": "2024\\2024-09-22_去了一趟月球",
            "end_time": "2025-08-26 12:20:22",
            "size_bytes": 1555015,
            "size_mb": 1.48,
            "duration_from_previous_seconds": 28.88
        },
        {
            "path": "2024\\2024-09-13_很精彩",
            "end_time": "2025-08-26 12:21:13",
            "size_bytes": 4782888,
            "size_mb": 4.56,
            "duration_from_previous_seconds": 50.47
        },
        {
            "path": "2024\\2024-09-03_留下尬走的足迹｜大湾区",
            "end_time": "2025-08-26 12:24:21",
            "size_bytes": 26565244,
            "size_mb": 25.33,
            "duration_from_previous_seconds": 188.66
        },
        {
            "path": "2024\\2024-08-22_留下尬走的足迹｜西马、新加坡",
            "end_time": "2025-08-26 12:25:48",
            "size_bytes": 9909005,
            "size_mb": 9.45,
            "duration_from_previous_seconds": 86.13
        },
        {
            "path": "2024\\2024-07-31_文不加点的张衔瑜七岁了",
            "end_time": "2025-08-26 12:26:03",
            "size_bytes": 161668,
            "size_mb": 0.15,
            "duration_from_previous_seconds": 15.84
        },
        {
            "path": "2024\\2024-07-28_梦到世纪大停电",
            "end_time": "2025-08-26 12:26:24",
            "size_bytes": 616507,
            "size_mb": 0.59,
            "duration_from_previous_seconds": 20.29
        },
        {
            "path": "2024\\2024-07-22_看电影",
            "end_time": "2025-08-26 12:27:12",
            "size_bytes": 3771884,
            "size_mb": 3.6,
            "duration_from_previous_seconds": 48.21
        },
        {
            "path": "2024\\2024-07-17_悟已往之不谏",
            "end_time": "2025-08-26 12:27:56",
            "size_bytes": 284772,
            "size_mb": 0.27,
            "duration_from_previous_seconds": 43.93
        },
        {
            "path": "2024\\2024-07-13_牛羊也下山了",
            "end_time": "2025-08-26 12:28:17",
            "size_bytes": 1099768,
            "size_mb": 1.05,
            "duration_from_previous_seconds": 21.65
        },
        {
            "path": "2024\\2024-07-08_梦",
            "end_time": "2025-08-26 12:28:38",
            "size_bytes": 259624,
            "size_mb": 0.25,
            "duration_from_previous_seconds": 20.96
        },
        {
            "path": "2024\\2024-07-05_忘",
            "end_time": "2025-08-26 12:29:00",
            "size_bytes": 738129,
            "size_mb": 0.7,
            "duration_from_previous_seconds": 21.43
        },
        {
            "path": "2024\\2024-06-30_赌",
            "end_time": "2025-08-26 12:29:21",
            "size_bytes": 272088,
            "size_mb": 0.26,
            "duration_from_previous_seconds": 21.13
        },
        {
            "path": "2024\\2024-06-27_趔趄",
            "end_time": "2025-08-26 12:29:41",
            "size_bytes": 257420,
            "size_mb": 0.25,
            "duration_from_previous_seconds": 20.1
        },
        {
            "path": "2024\\2024-06-23_船头跟我点点头",
            "end_time": "2025-08-26 12:30:00",
            "size_bytes": 228988,
            "size_mb": 0.22,
            "duration_from_previous_seconds": 18.81
        },
        {
            "path": "2024\\2024-06-17_打胡须膏的时候",
            "end_time": "2025-08-26 12:30:17",
            "size_bytes": 379275,
            "size_mb": 0.36,
            "duration_from_previous_seconds": 16.91
        },
        {
            "path": "2024\\2024-06-16_楼梯间有很重水蜜桃味",
            "end_time": "2025-08-26 12:30:35",
            "size_bytes": 381536,
            "size_mb": 0.36,
            "duration_from_previous_seconds": 17.92
        },
        {
            "path": "2024\\2024-06-13_戴降噪耳机听白噪音",
            "end_time": "2025-08-26 12:31:36",
            "size_bytes": 280343,
            "size_mb": 0.27,
            "duration_from_previous_seconds": 61.16
        },
        {
            "path": "2024\\2024-06-11_偷偷买西米露",
            "end_time": "2025-08-26 12:31:55",
            "size_bytes": 122081,
            "size_mb": 0.12,
            "duration_from_previous_seconds": 19.11
        },
        {
            "path": "2024\\2024-06-09_不打转向灯",
            "end_time": "2025-08-26 12:32:16",
            "size_bytes": 478085,
            "size_mb": 0.46,
            "duration_from_previous_seconds": 21.27
        },
        {
            "path": "2024\\2024-05-30_你又随地吐痰",
            "end_time": "2025-08-26 12:32:33",
            "size_bytes": 293707,
            "size_mb": 0.28,
            "duration_from_previous_seconds": 16.55
        },
        {
            "path": "2024\\2024-05-17_乱成一锅粥，喝粥",
            "end_time": "2025-08-26 12:32:55",
            "size_bytes": 380646,
            "size_mb": 0.36,
            "duration_from_previous_seconds": 22.06
        },
        {
            "path": "2024\\2024-05-06_红顶棚灰铁架",
            "end_time": "2025-08-26 12:33:15",
            "size_bytes": 257695,
            "size_mb": 0.25,
            "duration_from_previous_seconds": 20.56
        },
        {
            "path": "2024\\2024-05-01_脚底踩了个鞭炮",
            "end_time": "2025-08-26 12:33:33",
            "size_bytes": 28886,
            "size_mb": 0.03,
            "duration_from_previous_seconds": 17.47
        },
        {
            "path": "2024\\2024-04-22_下班后我就不戴眼镜了",
            "end_time": "2025-08-26 12:33:52",
            "size_bytes": 242210,
            "size_mb": 0.23,
            "duration_from_previous_seconds": 18.76
        },
        {
            "path": "2024\\2024-04-16_器物感",
            "end_time": "2025-08-26 12:34:10",
            "size_bytes": 80670,
            "size_mb": 0.08,
            "duration_from_previous_seconds": 18.75
        },
        {
            "path": "2024\\2024-04-07_连接",
            "end_time": "2025-08-26 12:34:37",
            "size_bytes": 1223625,
            "size_mb": 1.17,
            "duration_from_previous_seconds": 26.32
        },
        {
            "path": "2024\\2024-02-24_胡说八道的乐趣",
            "end_time": "2025-08-26 12:35:28",
            "size_bytes": 857537,
            "size_mb": 0.82,
            "duration_from_previous_seconds": 51.68
        },
        {
            "path": "2024\\2024-02-13_剪指甲",
            "end_time": "2025-08-26 12:35:47",
            "size_bytes": 389814,
            "size_mb": 0.37,
            "duration_from_previous_seconds": 19.07
        },
        {
            "path": "2024\\2024-02-06_一排路灯坏了好几个整流器",
            "end_time": "2025-08-26 12:36:06",
            "size_bytes": 268440,
            "size_mb": 0.26,
            "duration_from_previous_seconds": 18.95
        },
        {
            "path": "2024\\2024-01-29_盘盘焉，囷囷焉",
            "end_time": "2025-08-26 12:36:25",
            "size_bytes": 420925,
            "size_mb": 0.4,
            "duration_from_previous_seconds": 18.7
        },
        {
            "path": "2024\\2024-01-24_沙漠种草",
            "end_time": "2025-08-26 12:36:47",
            "size_bytes": 351351,
            "size_mb": 0.34,
            "duration_from_previous_seconds": 21.37
        },
        {
            "path": "2024\\2024-01-17_度百天，然后等夜晚",
            "end_time": "2025-08-26 12:37:11",
            "size_bytes": 803596,
            "size_mb": 0.77,
            "duration_from_previous_seconds": 24.67
        },
        {
            "path": "2024\\2024-01-05_荒腔走板",
            "end_time": "2025-08-26 12:37:32",
            "size_bytes": 768984,
            "size_mb": 0.73,
            "duration_from_previous_seconds": 20.63
        },
        {
            "path": "2023\\2023-12-29_只要内心远过空旷_100图和衔瑜的2023再见",
            "end_time": "2025-08-26 12:39:48",
            "size_bytes": 16427883,
            "size_mb": 15.67,
            "duration_from_previous_seconds": 136.18
        },
        {
            "path": "2023\\2023-12-21_树莓粉和捣练图",
            "end_time": "2025-08-26 12:40:08",
            "size_bytes": 537395,
            "size_mb": 0.51,
            "duration_from_previous_seconds": 19.53
        },
        {
            "path": "2023\\2023-12-12_眾鳥非鳥",
            "end_time": "2025-08-26 12:40:29",
            "size_bytes": 411644,
            "size_mb": 0.39,
            "duration_from_previous_seconds": 21.56
        },
        {
            "path": "2023\\2023-12-05_提问还是捕捉",
            "end_time": "2025-08-26 12:41:14",
            "size_bytes": 637515,
            "size_mb": 0.61,
            "duration_from_previous_seconds": 44.45
        },
        {
            "path": "2023\\2023-11-28_留下尬走的足迹｜｜雕门岛",
            "end_time": "2025-08-26 12:42:19",
            "size_bytes": 6060177,
            "size_mb": 5.78,
            "duration_from_previous_seconds": 64.99
        },
        {
            "path": "2023\\2023-11-20_盯着鞋子",
            "end_time": "2025-08-26 12:42:37",
            "size_bytes": 45966,
            "size_mb": 0.04,
            "duration_from_previous_seconds": 18.57
        },
        {
            "path": "2023\\2023-11-19_夸大风险评估",
            "end_time": "2025-08-26 12:43:12",
            "size_bytes": 2486619,
            "size_mb": 2.37,
            "duration_from_previous_seconds": 34.67
        },
        {
            "path": "2023\\2023-11-06_逛松弛感裤子越逛越紧张",
            "end_time": "2025-08-26 12:43:30",
            "size_bytes": 174808,
            "size_mb": 0.17,
            "duration_from_previous_seconds": 18.28
        },
        {
            "path": "2023\\2023-11-06_风能不能凉一点",
            "end_time": "2025-08-26 12:43:46",
            "size_bytes": 210944,
            "size_mb": 0.2,
            "duration_from_previous_seconds": 16.12
        },
        {
            "path": "2023\\2023-11-02_机锋多骗子",
            "end_time": "2025-08-26 12:44:09",
            "size_bytes": 792545,
            "size_mb": 0.76,
            "duration_from_previous_seconds": 22.99
        },
        {
            "path": "2023\\2023-10-19_回桌子前",
            "end_time": "2025-08-26 12:44:31",
            "size_bytes": 435279,
            "size_mb": 0.42,
            "duration_from_previous_seconds": 21.63
        },
        {
            "path": "2023\\2023-10-11_没擦通风口",
            "end_time": "2025-08-26 12:44:57",
            "size_bytes": 1019153,
            "size_mb": 0.97,
            "duration_from_previous_seconds": 26.49
        },
        {
            "path": "2023\\2023-10-06_但馄饨很烫",
            "end_time": "2025-08-26 12:45:19",
            "size_bytes": 342837,
            "size_mb": 0.33,
            "duration_from_previous_seconds": 21.46
        },
        {
            "path": "2023\\2023-09-14_先关电梯门，再按键",
            "end_time": "2025-08-26 12:46:05",
            "size_bytes": 289523,
            "size_mb": 0.28,
            "duration_from_previous_seconds": 46.71
        },
        {
            "path": "2023\\2023-09-04_心狠点下老贵外卖",
            "end_time": "2025-08-26 12:46:26",
            "size_bytes": 345376,
            "size_mb": 0.33,
            "duration_from_previous_seconds": 20.93
        },
        {
            "path": "2023\\2023-08-31_像一袋黄豆一样坐在那",
            "end_time": "2025-08-26 12:46:43",
            "size_bytes": 235179,
            "size_mb": 0.22,
            "duration_from_previous_seconds": 16.8
        },
        {
            "path": "2023\\2023-08-31_像一袋黄豆一样坐在那（GPT版）",
            "end_time": "2025-08-26 12:47:01",
            "size_bytes": 314566,
            "size_mb": 0.3,
            "duration_from_previous_seconds": 18.21
        },
        {
            "path": "2023\\2023-08-13_鬼画联翩",
            "end_time": "2025-08-26 12:47:19",
            "size_bytes": 260066,
            "size_mb": 0.25,
            "duration_from_previous_seconds": 18.0
        },
        {
            "path": "2023\\2023-07-30_文不加点的张衔瑜六岁了",
            "end_time": "2025-08-26 12:47:40",
            "size_bytes": 374409,
            "size_mb": 0.36,
            "duration_from_previous_seconds": 20.22
        },
        {
            "path": "2023\\2023-07-19_两部电影的观后小札",
            "end_time": "2025-08-26 12:47:57",
            "size_bytes": 297837,
            "size_mb": 0.28,
            "duration_from_previous_seconds": 17.77
        },
        {
            "path": "2023\\2023-07-06_萝卜快了不洗泥",
            "end_time": "2025-08-26 12:48:20",
            "size_bytes": 3188483,
            "size_mb": 3.04,
            "duration_from_previous_seconds": 22.78
        },
        {
            "path": "2023\\2023-06-14_被人说我干活时讲话就像英翻中",
            "end_time": "2025-08-26 12:48:38",
            "size_bytes": 191475,
            "size_mb": 0.18,
            "duration_from_previous_seconds": 18.03
        },
        {
            "path": "2023\\2023-06-08_留下尬走的足迹_苏州上海",
            "end_time": "2025-08-26 12:50:15",
            "size_bytes": 8284643,
            "size_mb": 7.9,
            "duration_from_previous_seconds": 96.42
        },
        {
            "path": "2023\\2023-06-07_留下尬走的足迹_福州",
            "end_time": "2025-08-26 12:51:33",
            "size_bytes": 6762104,
            "size_mb": 6.45,
            "duration_from_previous_seconds": 78.41
        },
        {
            "path": "2023\\2023-05-21_和农忙过年一样忙",
            "end_time": "2025-08-26 12:52:27",
            "size_bytes": 3612929,
            "size_mb": 3.45,
            "duration_from_previous_seconds": 53.84
        },
        {
            "path": "2023\\2023-05-11_罗生门之抽象",
            "end_time": "2025-08-26 12:52:44",
            "size_bytes": 1169341,
            "size_mb": 1.12,
            "duration_from_previous_seconds": 17.48
        },
        {
            "path": "2023\\2023-05-07_消遣",
            "end_time": "2025-08-26 12:52:59",
            "size_bytes": 16868,
            "size_mb": 0.02,
            "duration_from_previous_seconds": 14.45
        },
        {
            "path": "2023\\2023-04-30_再搞抽象",
            "end_time": "2025-08-26 12:53:23",
            "size_bytes": 1332647,
            "size_mb": 1.27,
            "duration_from_previous_seconds": 24.23
        },
        {
            "path": "2023\\2023-04-29_搞抽象",
            "end_time": "2025-08-26 12:53:45",
            "size_bytes": 940128,
            "size_mb": 0.9,
            "duration_from_previous_seconds": 21.62
        },
        {
            "path": "2023\\2023-04-17_朋友说看见炸烤串的很像我",
            "end_time": "2025-08-26 12:54:03",
            "size_bytes": 179496,
            "size_mb": 0.17,
            "duration_from_previous_seconds": 18.21
        },
        {
            "path": "2023\\2023-04-09_留下尬走的足迹_新山",
            "end_time": "2025-08-26 12:55:10",
            "size_bytes": 5902114,
            "size_mb": 5.63,
            "duration_from_previous_seconds": 67.4
        },
        {
            "path": "2023\\2023-04-02_实验室对我来说是间网吧",
            "end_time": "2025-08-26 12:55:32",
            "size_bytes": 874968,
            "size_mb": 0.83,
            "duration_from_previous_seconds": 22.13
        },
        {
            "path": "2023\\2023-03-27_留下尬走的足迹_迪沙鲁",
            "end_time": "2025-08-26 12:56:32",
            "size_bytes": 6477830,
            "size_mb": 6.18,
            "duration_from_previous_seconds": 59.68
        },
        {
            "path": "2023\\2023-03-17_闭着眼睛坐公交车",
            "end_time": "2025-08-26 12:56:50",
            "size_bytes": 179347,
            "size_mb": 0.17,
            "duration_from_previous_seconds": 18.25
        },
        {
            "path": "2023\\2023-03-13_打算每周运动三次",
            "end_time": "2025-08-26 12:57:37",
            "size_bytes": 325577,
            "size_mb": 0.31,
            "duration_from_previous_seconds": 46.64
        },
        {
            "path": "2023\\2023-02-26_构思一个身份、然后出门",
            "end_time": "2025-08-26 12:58:06",
            "size_bytes": 2500631,
            "size_mb": 2.38,
            "duration_from_previous_seconds": 28.97
        },
        {
            "path": "2023\\2023-02-19_一行文字要读两遍",
            "end_time": "2025-08-26 12:58:51",
            "size_bytes": 2577805,
            "size_mb": 2.46,
            "duration_from_previous_seconds": 45.31
        },
        {
            "path": "2023\\2023-02-10_தைப்பூசம்大宝森节行记(微恐慎入",
            "end_time": "2025-08-26 13:00:12",
            "size_bytes": 10027148,
            "size_mb": 9.56,
            "duration_from_previous_seconds": 81.21
        },
        {
            "path": "2023\\2023-01-24_连日降水",
            "end_time": "2025-08-26 13:00:29",
            "size_bytes": 12959,
            "size_mb": 0.01,
            "duration_from_previous_seconds": 16.92
        },
        {
            "path": "2022\\2022-12-29_升降机送上一桶水泥_100图和衔瑜的2022再见",
            "end_time": "2025-08-26 13:02:41",
            "size_bytes": 31090547,
            "size_mb": 29.65,
            "duration_from_previous_seconds": 131.71
        },
        {
            "path": "2022\\2022-12-22_奇怪的人生经历增加了",
            "end_time": "2025-08-26 13:03:42",
            "size_bytes": 4740575,
            "size_mb": 4.52,
            "duration_from_previous_seconds": 61.29
        },
        {
            "path": "2022\\2022-12-07_击鼓传花",
            "end_time": "2025-08-26 13:04:07",
            "size_bytes": 502015,
            "size_mb": 0.48,
            "duration_from_previous_seconds": 25.0
        },
        {
            "path": "2022\\2022-12-02_眼神聚焦是一件难事",
            "end_time": "2025-08-26 13:04:28",
            "size_bytes": 730750,
            "size_mb": 0.7,
            "duration_from_previous_seconds": 20.34
        },
        {
            "path": "2022\\2022-11-25_悲伤蛙出镜好多次",
            "end_time": "2025-08-26 13:04:49",
            "size_bytes": 845777,
            "size_mb": 0.81,
            "duration_from_previous_seconds": 21.55
        },
        {
            "path": "2022\\2022-11-04_压力大就去公厕捶门",
            "end_time": "2025-08-26 13:05:42",
            "size_bytes": 851764,
            "size_mb": 0.81,
            "duration_from_previous_seconds": 53.24
        },
        {
            "path": "2022\\2022-10-09_逻人",
            "end_time": "2025-08-26 13:06:20",
            "size_bytes": 2265954,
            "size_mb": 2.16,
            "duration_from_previous_seconds": 37.54
        },
        {
            "path": "2022\\2022-09-29_烧炕还是做饭，这么废柴",
            "end_time": "2025-08-26 13:06:37",
            "size_bytes": 535990,
            "size_mb": 0.51,
            "duration_from_previous_seconds": 17.08
        },
        {
            "path": "2022\\2022-09-21_这个天气骑车还有点冷",
            "end_time": "2025-08-26 13:06:56",
            "size_bytes": 1331710,
            "size_mb": 1.27,
            "duration_from_previous_seconds": 18.56
        },
        {
            "path": "2022\\2022-09-18_在公园长椅睡觉才是正经事",
            "end_time": "2025-08-26 13:07:39",
            "size_bytes": 2487783,
            "size_mb": 2.37,
            "duration_from_previous_seconds": 43.14
        },
        {
            "path": "2022\\2022-09-09_严禁盗采盗伐",
            "end_time": "2025-08-26 13:08:04",
            "size_bytes": 2521743,
            "size_mb": 2.4,
            "duration_from_previous_seconds": 25.13
        },
        {
            "path": "2022\\2022-09-07_一团薯泥",
            "end_time": "2025-08-26 13:08:26",
            "size_bytes": 258793,
            "size_mb": 0.25,
            "duration_from_previous_seconds": 21.75
        },
        {
            "path": "2022\\2022-08-29_像后台进程，占不多、但无穷尽、而且找不着",
            "end_time": "2025-08-26 13:08:54",
            "size_bytes": 969886,
            "size_mb": 0.92,
            "duration_from_previous_seconds": 28.24
        },
        {
            "path": "2022\\2022-08-19_留下尬走的足迹_第很多次到北京",
            "end_time": "2025-08-26 13:10:27",
            "size_bytes": 9030369,
            "size_mb": 8.61,
            "duration_from_previous_seconds": 92.74
        },
        {
            "path": "2022\\2022-07-31_文不加点的张衔瑜五岁了",
            "end_time": "2025-08-26 13:10:44",
            "size_bytes": 62737,
            "size_mb": 0.06,
            "duration_from_previous_seconds": 17.58
        },
        {
            "path": "2022\\2022-07-30_留下尬走的足迹_川西入云龙",
            "end_time": "2025-08-26 13:15:10",
            "size_bytes": 29312977,
            "size_mb": 27.96,
            "duration_from_previous_seconds": 266.15
        },
        {
            "path": "2022\\2022-07-03_原来如实",
            "end_time": "2025-08-26 13:15:49",
            "size_bytes": 380838,
            "size_mb": 0.36,
            "duration_from_previous_seconds": 38.24
        },
        {
            "path": "2022\\2022-06-26_消失在人海",
            "end_time": "2025-08-26 13:16:29",
            "size_bytes": 2226572,
            "size_mb": 2.12,
            "duration_from_previous_seconds": 40.85
        },
        {
            "path": "2022\\2022-06-12_有人路过那里",
            "end_time": "2025-08-26 13:16:52",
            "size_bytes": 535858,
            "size_mb": 0.51,
            "duration_from_previous_seconds": 22.73
        },
        {
            "path": "2022\\2022-05-27_道拉基",
            "end_time": "2025-08-26 13:17:58",
            "size_bytes": 5977963,
            "size_mb": 5.7,
            "duration_from_previous_seconds": 65.96
        },
        {
            "path": "2022\\2022-05-20_没有遗憾了才可以睡觉",
            "end_time": "2025-08-26 13:22:08",
            "size_bytes": 22676538,
            "size_mb": 21.63,
            "duration_from_previous_seconds": 249.72
        },
        {
            "path": "2022\\2022-05-08_拼凑的碎片不能叫整体",
            "end_time": "2025-08-26 13:22:24",
            "size_bytes": 109280,
            "size_mb": 0.1,
            "duration_from_previous_seconds": 16.35
        },
        {
            "path": "2022\\2022-04-20_留下尬走的足迹_湘西",
            "end_time": "2025-08-26 13:26:01",
            "size_bytes": 27413836,
            "size_mb": 26.14,
            "duration_from_previous_seconds": 216.56
        },
        {
            "path": "2022\\2022-04-08_你说什么叫路径依赖",
            "end_time": "2025-08-26 13:26:21",
            "size_bytes": 206531,
            "size_mb": 0.2,
            "duration_from_previous_seconds": 20.17
        },
        {
            "path": "2022\\2022-03-17_焦虑突破了血脑屏障",
            "end_time": "2025-08-26 13:27:19",
            "size_bytes": 484221,
            "size_mb": 0.46,
            "duration_from_previous_seconds": 57.76
        },
        {
            "path": "2022\\2022-03-06_光彩奇异的三月生活",
            "end_time": "2025-08-26 13:28:00",
            "size_bytes": 3453822,
            "size_mb": 3.29,
            "duration_from_previous_seconds": 40.83
        },
        {
            "path": "2022\\2022-02-19_闲聊波尔卡",
            "end_time": "2025-08-26 13:28:17",
            "size_bytes": 315287,
            "size_mb": 0.3,
            "duration_from_previous_seconds": 17.77
        },
        {
            "path": "2022\\2022-02-12_我也会自转和公转",
            "end_time": "2025-08-26 13:28:40",
            "size_bytes": 1531616,
            "size_mb": 1.46,
            "duration_from_previous_seconds": 22.88
        },
        {
            "path": "2022\\2022-02-08_什么可以是一味安定？书店吗",
            "end_time": "2025-08-26 13:29:03",
            "size_bytes": 989675,
            "size_mb": 0.94,
            "duration_from_previous_seconds": 22.67
        },
        {
            "path": "2022\\2022-01-20_严丝密缝仍是最大问题",
            "end_time": "2025-08-26 13:29:26",
            "size_bytes": 1212229,
            "size_mb": 1.16,
            "duration_from_previous_seconds": 23.57
        },
        {
            "path": "2022\\2022-01-10_我发现实际上来说今天开学了",
            "end_time": "2025-08-26 13:29:47",
            "size_bytes": 502949,
            "size_mb": 0.48,
            "duration_from_previous_seconds": 21.0
        },
        {
            "path": "2021\\2021-12-30_梦把我从万花筒坠落_100图和衔瑜的2021再见",
            "end_time": "2025-08-26 13:31:50",
            "size_bytes": 12811118,
            "size_mb": 12.22,
            "duration_from_previous_seconds": 122.83
        },
        {
            "path": "2021\\2021-12-27_留下尬走的足迹_山西北段中段",
            "end_time": "2025-08-26 13:34:32",
            "size_bytes": 22113397,
            "size_mb": 21.09,
            "duration_from_previous_seconds": 161.82
        },
        {
            "path": "2021\\2021-12-07_留下尬走的足迹_南京镇江扬州盐城南通",
            "end_time": "2025-08-26 13:36:08",
            "size_bytes": 12640731,
            "size_mb": 12.06,
            "duration_from_previous_seconds": 95.76
        },
        {
            "path": "2021\\2021-11-24_留下尬走的足迹_宁波义乌杭州贵阳",
            "end_time": "2025-08-26 13:38:18",
            "size_bytes": 13783335,
            "size_mb": 13.14,
            "duration_from_previous_seconds": 130.4
        },
        {
            "path": "2021\\2021-11-16_气温每降低一度，炒板栗店就多一队人",
            "end_time": "2025-08-26 13:38:38",
            "size_bytes": 145848,
            "size_mb": 0.14,
            "duration_from_previous_seconds": 19.6
        },
        {
            "path": "2021\\2021-11-08_留下尬走的足迹_梅州汕头",
            "end_time": "2025-08-26 13:40:02",
            "size_bytes": 7120310,
            "size_mb": 6.79,
            "duration_from_previous_seconds": 83.76
        },
        {
            "path": "2021\\2021-11-02_留下尬走的足迹_北海涠洲南宁上海",
            "end_time": "2025-08-26 13:41:49",
            "size_bytes": 9132686,
            "size_mb": 8.71,
            "duration_from_previous_seconds": 107.24
        },
        {
            "path": "2021\\2021-10-17_哪能什么细节都严丝密缝",
            "end_time": "2025-08-26 13:42:52",
            "size_bytes": 5544205,
            "size_mb": 5.29,
            "duration_from_previous_seconds": 63.55
        },
        {
            "path": "2021\\2021-10-02_留下尬走的足迹_敦煌",
            "end_time": "2025-08-26 13:44:00",
            "size_bytes": 5635583,
            "size_mb": 5.37,
            "duration_from_previous_seconds": 67.46
        },
        {
            "path": "2021\\2021-09-20_没头没尾",
            "end_time": "2025-08-26 13:44:30",
            "size_bytes": 1477308,
            "size_mb": 1.41,
            "duration_from_previous_seconds": 30.33
        },
        {
            "path": "2021\\2021-09-12_耳朵占线",
            "end_time": "2025-08-26 13:45:01",
            "size_bytes": 1441259,
            "size_mb": 1.37,
            "duration_from_previous_seconds": 30.58
        },
        {
            "path": "2021\\2021-09-11_留下尬走的足迹_桂林",
            "end_time": "2025-08-26 13:45:37",
            "size_bytes": 2505062,
            "size_mb": 2.39,
            "duration_from_previous_seconds": 36.03
        },
        {
            "path": "2021\\2021-08-21_写段子是一回事",
            "end_time": "2025-08-26 13:45:57",
            "size_bytes": 317635,
            "size_mb": 0.3,
            "duration_from_previous_seconds": 20.68
        },
        {
            "path": "2021\\2021-08-04_听君一席话，白听一席话",
            "end_time": "2025-08-26 13:47:50",
            "size_bytes": 8042819,
            "size_mb": 7.67,
            "duration_from_previous_seconds": 112.22
        },
        {
            "path": "2021\\2021-07-31_文不加点的张衔瑜四岁了",
            "end_time": "2025-08-26 13:48:07",
            "size_bytes": 138329,
            "size_mb": 0.13,
            "duration_from_previous_seconds": 17.51
        },
        {
            "path": "2021\\2021-07-24_留下尬走的足迹_天津北京武汉",
            "end_time": "2025-08-26 13:49:44",
            "size_bytes": 8870151,
            "size_mb": 8.46,
            "duration_from_previous_seconds": 96.65
        },
        {
            "path": "2021\\2021-07-16_尽量少用偏正短语",
            "end_time": "2025-08-26 13:50:03",
            "size_bytes": 172107,
            "size_mb": 0.16,
            "duration_from_previous_seconds": 18.74
        },
        {
            "path": "2021\\2021-06-20_世界丰富而有锐度",
            "end_time": "2025-08-26 13:50:26",
            "size_bytes": 631448,
            "size_mb": 0.6,
            "duration_from_previous_seconds": 23.45
        },
        {
            "path": "2021\\2021-06-17_留下尬走的足迹_再到北京",
            "end_time": "2025-08-26 13:51:32",
            "size_bytes": 5285366,
            "size_mb": 5.04,
            "duration_from_previous_seconds": 65.56
        },
        {
            "path": "2021\\2021-05-25_忘性大的人不会老",
            "end_time": "2025-08-26 13:51:48",
            "size_bytes": 99290,
            "size_mb": 0.09,
            "duration_from_previous_seconds": 16.31
        },
        {
            "path": "2021\\2021-05-21_要拐几个弯幽默才幽默",
            "end_time": "2025-08-26 13:52:03",
            "size_bytes": 132974,
            "size_mb": 0.13,
            "duration_from_previous_seconds": 15.26
        },
        {
            "path": "2021\\2021-05-02_饭是打包的 但生活不是",
            "end_time": "2025-08-26 13:52:23",
            "size_bytes": 140663,
            "size_mb": 0.13,
            "duration_from_previous_seconds": 19.96
        },
        {
            "path": "2021\\2021-04-29_晒得人灭涝的",
            "end_time": "2025-08-26 13:52:57",
            "size_bytes": 985464,
            "size_mb": 0.94,
            "duration_from_previous_seconds": 33.66
        },
        {
            "path": "2021\\2021-04-13_回车键诗人",
            "end_time": "2025-08-26 13:53:43",
            "size_bytes": 215242,
            "size_mb": 0.21,
            "duration_from_previous_seconds": 46.56
        },
        {
            "path": "2021\\2021-04-06_最近每天下午都会下一阵雨",
            "end_time": "2025-08-26 13:54:03",
            "size_bytes": 204310,
            "size_mb": 0.19,
            "duration_from_previous_seconds": 20.18
        },
        {
            "path": "2021\\2021-04-03_电梯门开",
            "end_time": "2025-08-26 13:54:36",
            "size_bytes": 1366951,
            "size_mb": 1.3,
            "duration_from_previous_seconds": 32.05
        },
        {
            "path": "2021\\2021-03-30_智商散装[图]出入",
            "end_time": "2025-08-26 13:55:26",
            "size_bytes": 2435183,
            "size_mb": 2.32,
            "duration_from_previous_seconds": 50.37
        },
        {
            "path": "2021\\2021-03-26_有了上顿盼下顿",
            "end_time": "2025-08-26 13:55:44",
            "size_bytes": 305449,
            "size_mb": 0.29,
            "duration_from_previous_seconds": 18.43
        },
        {
            "path": "2021\\2021-03-18_盐王爷",
            "end_time": "2025-08-26 13:56:13",
            "size_bytes": 1953058,
            "size_mb": 1.86,
            "duration_from_previous_seconds": 28.75
        },
        {
            "path": "2021\\2021-03-15_你还(huán)什么咯？",
            "end_time": "2025-08-26 13:56:44",
            "size_bytes": 1681655,
            "size_mb": 1.6,
            "duration_from_previous_seconds": 31.33
        },
        {
            "path": "2021\\2021-03-05_一杯过饱和又不断析出的溶液",
            "end_time": "2025-08-26 13:57:18",
            "size_bytes": 1419385,
            "size_mb": 1.35,
            "duration_from_previous_seconds": 33.68
        },
        {
            "path": "2021\\2021-02-22_熬白天",
            "end_time": "2025-08-26 13:57:37",
            "size_bytes": 184002,
            "size_mb": 0.18,
            "duration_from_previous_seconds": 18.49
        },
        {
            "path": "2021\\2021-02-14_在坡的辛丑新年",
            "end_time": "2025-08-26 13:58:18",
            "size_bytes": 7040955,
            "size_mb": 6.71,
            "duration_from_previous_seconds": 41.36
        },
        {
            "path": "2021\\2021-02-10_一杯Kopi C Kosong也还是困",
            "end_time": "2025-08-26 13:59:08",
            "size_bytes": 1066157,
            "size_mb": 1.02,
            "duration_from_previous_seconds": 50.39
        },
        {
            "path": "2021\\2021-02-05_好久没吃杨枝甘露",
            "end_time": "2025-08-26 13:59:36",
            "size_bytes": 1570256,
            "size_mb": 1.5,
            "duration_from_previous_seconds": 27.54
        },
        {
            "path": "2021\\2021-02-03_降落幕布",
            "end_time": "2025-08-26 13:59:55",
            "size_bytes": 286388,
            "size_mb": 0.27,
            "duration_from_previous_seconds": 18.62
        },
        {
            "path": "2021\\2021-01-24_房间里有书香味，都不想出去",
            "end_time": "2025-08-26 14:00:29",
            "size_bytes": 767682,
            "size_mb": 0.73,
            "duration_from_previous_seconds": 34.64
        },
        {
            "path": "2021\\2021-01-19_一杯橘子汽水就能灌满外耳道",
            "end_time": "2025-08-26 14:00:46",
            "size_bytes": 16491,
            "size_mb": 0.02,
            "duration_from_previous_seconds": 16.55
        },
        {
            "path": "2021\\2021-01-17_醒，在想等会儿梦什么",
            "end_time": "2025-08-26 14:01:08",
            "size_bytes": 203179,
            "size_mb": 0.19,
            "duration_from_previous_seconds": 22.7
        },
        {
            "path": "2021\\2021-01-08_踩爆地上的牛奶盒",
            "end_time": "2025-08-26 14:01:27",
            "size_bytes": 168678,
            "size_mb": 0.16,
            "duration_from_previous_seconds": 18.55
        },
        {
            "path": "2020\\2020-12-30_你说别追呀又依依不舍_100图和衔瑜的2020再见",
            "end_time": "2025-08-26 14:03:39",
            "size_bytes": 17094129,
            "size_mb": 16.3,
            "duration_from_previous_seconds": 131.97
        },
        {
            "path": "2020\\2020-12-19_生是我的五花肉，熟是我的回锅肉",
            "end_time": "2025-08-26 14:04:09",
            "size_bytes": 1446344,
            "size_mb": 1.38,
            "duration_from_previous_seconds": 29.65
        },
        {
            "path": "2020\\2020-12-16_这哪是回笼觉？这是猪笼觉。",
            "end_time": "2025-08-26 14:04:26",
            "size_bytes": 46940,
            "size_mb": 0.04,
            "duration_from_previous_seconds": 17.05
        },
        {
            "path": "2020\\2020-12-14_不存在夜宵当晚餐的说法",
            "end_time": "2025-08-26 14:05:12",
            "size_bytes": 279728,
            "size_mb": 0.27,
            "duration_from_previous_seconds": 46.53
        },
        {
            "path": "2020\\2020-12-10_地铁看书，坐过了要下的站 _ 2020年书单",
            "end_time": "2025-08-26 14:05:29",
            "size_bytes": 83228,
            "size_mb": 0.08,
            "duration_from_previous_seconds": 17.21
        },
        {
            "path": "2020\\2020-12-01_导航：请在合适位置掉头",
            "end_time": "2025-08-26 14:05:56",
            "size_bytes": 921114,
            "size_mb": 0.88,
            "duration_from_previous_seconds": 27.08
        },
        {
            "path": "2020\\2020-11-26_在机场等一艘船来",
            "end_time": "2025-08-26 14:06:27",
            "size_bytes": 4233352,
            "size_mb": 4.04,
            "duration_from_previous_seconds": 30.52
        },
        {
            "path": "2020\\2020-11-20_和任何一种生活摩擦久了，都会起球",
            "end_time": "2025-08-26 14:06:44",
            "size_bytes": 231260,
            "size_mb": 0.22,
            "duration_from_previous_seconds": 16.57
        },
        {
            "path": "2020\\2020-11-17_印裔的新年：一场表演力的狂欢",
            "end_time": "2025-08-26 14:08:00",
            "size_bytes": 4851442,
            "size_mb": 4.63,
            "duration_from_previous_seconds": 76.51
        },
        {
            "path": "2020\\2020-11-10_人山人海，边走边忘",
            "end_time": "2025-08-26 14:08:18",
            "size_bytes": 269283,
            "size_mb": 0.26,
            "duration_from_previous_seconds": 18.27
        },
        {
            "path": "2020\\2020-11-08_夏天的立冬",
            "end_time": "2025-08-26 14:08:37",
            "size_bytes": 140818,
            "size_mb": 0.13,
            "duration_from_previous_seconds": 18.91
        },
        {
            "path": "2020\\2020-10-31_生 活 档 案 盒",
            "end_time": "2025-08-26 14:11:16",
            "size_bytes": 17003013,
            "size_mb": 16.22,
            "duration_from_previous_seconds": 159.16
        },
        {
            "path": "2020\\2020-10-17_最近有在拍照，也做一些运动",
            "end_time": "2025-08-26 14:15:40",
            "size_bytes": 14718543,
            "size_mb": 14.04,
            "duration_from_previous_seconds": 263.96
        },
        {
            "path": "2020\\2020-10-05_因为春天很闲，秋天很累",
            "end_time": "2025-08-26 14:17:48",
            "size_bytes": 9322818,
            "size_mb": 8.89,
            "duration_from_previous_seconds": 127.76
        },
        {
            "path": "2020\\2020-09-28_喜欢一种风格就拿相机去拍到吐",
            "end_time": "2025-08-26 14:18:57",
            "size_bytes": 3478070,
            "size_mb": 3.32,
            "duration_from_previous_seconds": 68.4
        },
        {
            "path": "2020\\2020-09-19_每一个胃都会谢谢你的努力",
            "end_time": "2025-08-26 14:19:22",
            "size_bytes": 609665,
            "size_mb": 0.58,
            "duration_from_previous_seconds": 25.71
        },
        {
            "path": "2020\\2020-09-13_今天喝了豆浆，还用微波炉热了面包",
            "end_time": "2025-08-26 14:19:49",
            "size_bytes": 817335,
            "size_mb": 0.78,
            "duration_from_previous_seconds": 27.02
        },
        {
            "path": "2020\\2020-09-12_摸鱼，是我最想传承的非物质文化遗产",
            "end_time": "2025-08-26 14:21:44",
            "size_bytes": 6189996,
            "size_mb": 5.9,
            "duration_from_previous_seconds": 114.58
        },
        {
            "path": "2020\\2020-09-03_一只壁虎钻进鞋柜不见",
            "end_time": "2025-08-26 14:23:29",
            "size_bytes": 6606190,
            "size_mb": 6.3,
            "duration_from_previous_seconds": 105.51
        },
        {
            "path": "2020\\2020-08-18_钝感隔离",
            "end_time": "2025-08-26 14:24:54",
            "size_bytes": 4956234,
            "size_mb": 4.73,
            "duration_from_previous_seconds": 84.7
        },
        {
            "path": "2020\\2020-08-15_日落会在夏天开放吗",
            "end_time": "2025-08-26 14:28:35",
            "size_bytes": 12703805,
            "size_mb": 12.12,
            "duration_from_previous_seconds": 221.32
        },
        {
            "path": "2020\\2020-07-31_文不加点的张衔瑜三岁了",
            "end_time": "2025-08-26 14:29:01",
            "size_bytes": 834046,
            "size_mb": 0.8,
            "duration_from_previous_seconds": 25.82
        },
        {
            "path": "2020\\2020-07-18_事件持续发酵，最后松软可口",
            "end_time": "2025-08-26 14:31:12",
            "size_bytes": 9750834,
            "size_mb": 9.3,
            "duration_from_previous_seconds": 131.17
        },
        {
            "path": "2020\\2020-07-02_時刻旅行。相册, 才保鮮",
            "end_time": "2025-08-26 14:34:38",
            "size_bytes": 11800095,
            "size_mb": 11.25,
            "duration_from_previous_seconds": 205.51
        },
        {
            "path": "2020\\2020-06-13_像复仇一样出门玩",
            "end_time": "2025-08-26 14:38:11",
            "size_bytes": 14956211,
            "size_mb": 14.26,
            "duration_from_previous_seconds": 213.41
        },
        {
            "path": "2020\\2020-05-29_西去翱翔的飞鸟",
            "end_time": "2025-08-26 14:39:27",
            "size_bytes": 3483159,
            "size_mb": 3.32,
            "duration_from_previous_seconds": 76.15
        },
        {
            "path": "2020\\2020-05-22_城市海绵",
            "end_time": "2025-08-26 14:42:47",
            "size_bytes": 15453187,
            "size_mb": 14.74,
            "duration_from_previous_seconds": 199.82
        },
        {
            "path": "2020\\2020-05-09_生活贼船上的快乐海盗",
            "end_time": "2025-08-26 14:44:37",
            "size_bytes": 10009346,
            "size_mb": 9.55,
            "duration_from_previous_seconds": 109.32
        },
        {
            "path": "2020\\2020-04-29_尝试用一句话解释复杂生活",
            "end_time": "2025-08-26 14:47:20",
            "size_bytes": 13517781,
            "size_mb": 12.89,
            "duration_from_previous_seconds": 163.93
        },
        {
            "path": "2020\\2020-04-18_走街 窜巷 寻坊 探店",
            "end_time": "2025-08-26 14:51:38",
            "size_bytes": 20976338,
            "size_mb": 20.0,
            "duration_from_previous_seconds": 257.45
        },
        {
            "path": "2020\\2020-04-18_最近睡很坏，最好困书店里",
            "end_time": "2025-08-26 14:53:23",
            "size_bytes": 8110989,
            "size_mb": 7.74,
            "duration_from_previous_seconds": 105.47
        },
        {
            "path": "2020\\2020-04-11_我的人文启蒙",
            "end_time": "2025-08-26 14:54:18",
            "size_bytes": 2914549,
            "size_mb": 2.78,
            "duration_from_previous_seconds": 54.94
        },
        {
            "path": "2020\\2020-03-30_留下尬走的足迹_湘南",
            "end_time": "2025-08-26 14:57:31",
            "size_bytes": 16414634,
            "size_mb": 15.65,
            "duration_from_previous_seconds": 192.25
        },
        {
            "path": "2020\\2020-03-24_大心话 真冒险",
            "end_time": "2025-08-26 15:00:13",
            "size_bytes": 11737859,
            "size_mb": 11.19,
            "duration_from_previous_seconds": 162.09
        },
        {
            "path": "2020\\2020-03-17_当创意漂浮起来",
            "end_time": "2025-08-26 15:03:00",
            "size_bytes": 16944003,
            "size_mb": 16.16,
            "duration_from_previous_seconds": 167.75
        },
        {
            "path": "2020\\2020-03-08_三月上的视觉收纳",
            "end_time": "2025-08-26 15:04:31",
            "size_bytes": 4514291,
            "size_mb": 4.31,
            "duration_from_previous_seconds": 90.58
        },
        {
            "path": "2020\\2020-03-02_情绪过载",
            "end_time": "2025-08-26 15:05:21",
            "size_bytes": 1749135,
            "size_mb": 1.67,
            "duration_from_previous_seconds": 49.94
        },
        {
            "path": "2020\\2020-02-21_旧簿考古",
            "end_time": "2025-08-26 15:06:04",
            "size_bytes": 2712232,
            "size_mb": 2.59,
            "duration_from_previous_seconds": 42.9
        },
        {
            "path": "2020\\2020-02-14_鸡皮蒜毛分享家",
            "end_time": "2025-08-26 15:06:34",
            "size_bytes": 1027241,
            "size_mb": 0.98,
            "duration_from_previous_seconds": 29.83
        },
        {
            "path": "2020\\2020-02-10_人不堪其忧，我也不改其乐",
            "end_time": "2025-08-26 15:07:21",
            "size_bytes": 2137319,
            "size_mb": 2.04,
            "duration_from_previous_seconds": 46.84
        },
        {
            "path": "2020\\2020-02-07_情绪洪流下，阅卷反馈最近的命题作文",
            "end_time": "2025-08-26 15:07:41",
            "size_bytes": 376514,
            "size_mb": 0.36,
            "duration_from_previous_seconds": 20.72
        },
        {
            "path": "2020\\2020-02-04_把生活的书页翻得哗啦啦地响",
            "end_time": "2025-08-26 15:08:08",
            "size_bytes": 1092448,
            "size_mb": 1.04,
            "duration_from_previous_seconds": 26.51
        },
        {
            "path": "2020\\2020-01-29_自由二字，长得条条框框",
            "end_time": "2025-08-26 15:10:46",
            "size_bytes": 12329638,
            "size_mb": 11.76,
            "duration_from_previous_seconds": 158.16
        },
        {
            "path": "2020\\2020-01-12_​留下尬走的足迹_南京",
            "end_time": "2025-08-26 15:14:09",
            "size_bytes": 14089971,
            "size_mb": 13.44,
            "duration_from_previous_seconds": 203.42
        },
        {
            "path": "2020\\2020-01-01_你告诉我理想必须热爱_100图和衔瑜的2019再见",
            "end_time": "2025-08-26 15:16:21",
            "size_bytes": 12845468,
            "size_mb": 12.25,
            "duration_from_previous_seconds": 131.69
        },
        {
            "path": "2019\\2019-12-28_恶性社会事件，不必变相“荡妇羞辱”自己",
            "end_time": "2025-08-26 15:16:39",
            "size_bytes": 180562,
            "size_mb": 0.17,
            "duration_from_previous_seconds": 17.77
        },
        {
            "path": "2019\\2019-12-27_留下尬走的足迹_襄阳",
            "end_time": "2025-08-26 15:18:01",
            "size_bytes": 5314375,
            "size_mb": 5.07,
            "duration_from_previous_seconds": 82.11
        },
        {
            "path": "2019\\2019-12-19_恰到好处的悲伤胜过哭天抢地的哀嚎",
            "end_time": "2025-08-26 15:18:23",
            "size_bytes": 720423,
            "size_mb": 0.69,
            "duration_from_previous_seconds": 22.43
        },
        {
            "path": "2019\\2019-12-06_我饿了。看来漂亮不能当饭吃。",
            "end_time": "2025-08-26 15:19:15",
            "size_bytes": 3455418,
            "size_mb": 3.3,
            "duration_from_previous_seconds": 52.11
        },
        {
            "path": "2019\\2019-11-29_人一胖，看书都像读菜单",
            "end_time": "2025-08-26 15:19:39",
            "size_bytes": 397397,
            "size_mb": 0.38,
            "duration_from_previous_seconds": 23.1
        },
        {
            "path": "2019\\2019-11-23_冬郁症",
            "end_time": "2025-08-26 15:20:01",
            "size_bytes": 753924,
            "size_mb": 0.72,
            "duration_from_previous_seconds": 21.99
        },
        {
            "path": "2019\\2019-11-15_穿着衬衫睡觉",
            "end_time": "2025-08-26 15:20:26",
            "size_bytes": 387397,
            "size_mb": 0.37,
            "duration_from_previous_seconds": 25.65
        },
        {
            "path": "2019\\2019-11-14_重症自闭：成为自己的NPC",
            "end_time": "2025-08-26 15:20:54",
            "size_bytes": 1443556,
            "size_mb": 1.38,
            "duration_from_previous_seconds": 27.62
        },
        {
            "path": "2019\\2019-11-09_攒够了失望",
            "end_time": "2025-08-26 15:22:20",
            "size_bytes": 3319137,
            "size_mb": 3.17,
            "duration_from_previous_seconds": 85.74
        },
        {
            "path": "2019\\2019-11-03_没必要抱有希望，没必要不抱希望",
            "end_time": "2025-08-26 15:22:46",
            "size_bytes": 728539,
            "size_mb": 0.69,
            "duration_from_previous_seconds": 26.65
        },
        {
            "path": "2019\\2019-10-28_今天犯点什么坏呢？",
            "end_time": "2025-08-26 15:23:13",
            "size_bytes": 655976,
            "size_mb": 0.63,
            "duration_from_previous_seconds": 26.33
        },
        {
            "path": "2019\\2019-10-21_路灯底下，没有我要找的钥匙",
            "end_time": "2025-08-26 15:23:40",
            "size_bytes": 680744,
            "size_mb": 0.65,
            "duration_from_previous_seconds": 27.21
        },
        {
            "path": "2019\\2019-10-12_我吃饭的时候不饿",
            "end_time": "2025-08-26 15:24:12",
            "size_bytes": 1595376,
            "size_mb": 1.52,
            "duration_from_previous_seconds": 32.18
        },
        {
            "path": "2019\\2019-10-09_为什么要怕鬼？害你的全是人。",
            "end_time": "2025-08-26 15:24:46",
            "size_bytes": 1210061,
            "size_mb": 1.15,
            "duration_from_previous_seconds": 34.32
        },
        {
            "path": "2019\\2019-09-28_过气迷惑战士",
            "end_time": "2025-08-26 15:25:12",
            "size_bytes": 382399,
            "size_mb": 0.36,
            "duration_from_previous_seconds": 25.67
        },
        {
            "path": "2019\\2019-09-26_一天过完，绕着远路回去",
            "end_time": "2025-08-26 15:25:39",
            "size_bytes": 707850,
            "size_mb": 0.68,
            "duration_from_previous_seconds": 27.02
        },
        {
            "path": "2019\\2019-09-22_留下尬走的足迹_兰州",
            "end_time": "2025-08-26 15:26:17",
            "size_bytes": 2092689,
            "size_mb": 2.0,
            "duration_from_previous_seconds": 37.71
        },
        {
            "path": "2019\\2019-09-14_留下尬走的足迹_厦门",
            "end_time": "2025-08-26 15:27:27",
            "size_bytes": 7209905,
            "size_mb": 6.88,
            "duration_from_previous_seconds": 70.36
        },
        {
            "path": "2019\\2019-09-14_留下尬走的足迹_皖赣边界",
            "end_time": "2025-08-26 15:28:38",
            "size_bytes": 3426340,
            "size_mb": 3.27,
            "duration_from_previous_seconds": 71.5
        },
        {
            "path": "2019\\2019-08-30_唱片店回忆札",
            "end_time": "2025-08-26 15:29:09",
            "size_bytes": 1509017,
            "size_mb": 1.44,
            "duration_from_previous_seconds": 30.97
        },
        {
            "path": "2019\\2019-08-26_留下尬走的足迹_香港、深圳",
            "end_time": "2025-08-26 15:29:46",
            "size_bytes": 2093241,
            "size_mb": 2.0,
            "duration_from_previous_seconds": 36.73
        },
        {
            "path": "2019\\2019-08-18_与恶，只有一点点距离",
            "end_time": "2025-08-26 15:30:20",
            "size_bytes": 1215210,
            "size_mb": 1.16,
            "duration_from_previous_seconds": 34.25
        },
        {
            "path": "2019\\2019-07-31_文不加点的张衔瑜两岁了",
            "end_time": "2025-08-26 15:30:49",
            "size_bytes": 737987,
            "size_mb": 0.7,
            "duration_from_previous_seconds": 28.85
        },
        {
            "path": "2019\\2019-07-29_一只沙雕叼走了一颗栗子",
            "end_time": "2025-08-26 15:31:12",
            "size_bytes": 1716686,
            "size_mb": 1.64,
            "duration_from_previous_seconds": 22.31
        },
        {
            "path": "2019\\2019-07-24_空腹的人可以吃饭吗？",
            "end_time": "2025-08-26 15:31:32",
            "size_bytes": 431501,
            "size_mb": 0.41,
            "duration_from_previous_seconds": 20.49
        },
        {
            "path": "2019\\2019-07-21_青春万岁，都要颗粒归仓",
            "end_time": "2025-08-26 15:32:06",
            "size_bytes": 931327,
            "size_mb": 0.89,
            "duration_from_previous_seconds": 33.86
        },
        {
            "path": "2019\\2019-07-19_凌晨一点、卸下伪装、露出素颜，称为“丑时”",
            "end_time": "2025-08-26 15:32:45",
            "size_bytes": 381341,
            "size_mb": 0.36,
            "duration_from_previous_seconds": 39.21
        },
        {
            "path": "2019\\2019-07-15_小张小张，卑微开张",
            "end_time": "2025-08-26 15:33:10",
            "size_bytes": 841286,
            "size_mb": 0.8,
            "duration_from_previous_seconds": 25.27
        },
        {
            "path": "2019\\2019-07-09_小张小张，从不慌张",
            "end_time": "2025-08-26 15:33:58",
            "size_bytes": 536328,
            "size_mb": 0.51,
            "duration_from_previous_seconds": 47.25
        },
        {
            "path": "2019\\2019-07-07_疲劳驾驶一千两百公里",
            "end_time": "2025-08-26 15:34:23",
            "size_bytes": 756071,
            "size_mb": 0.72,
            "duration_from_previous_seconds": 25.0
        },
        {
            "path": "2019\\2019-06-29_打翻可乐后又蹭倒了椅子",
            "end_time": "2025-08-26 15:34:47",
            "size_bytes": 728370,
            "size_mb": 0.69,
            "duration_from_previous_seconds": 24.46
        },
        {
            "path": "2019\\2019-06-25_能够正常安分地过完，就已经是个奇迹了",
            "end_time": "2025-08-26 15:35:15",
            "size_bytes": 634983,
            "size_mb": 0.61,
            "duration_from_previous_seconds": 27.95
        },
        {
            "path": "2019\\2019-06-22_雨季，转凉的下午，等不到放晴",
            "end_time": "2025-08-26 15:35:46",
            "size_bytes": 1021556,
            "size_mb": 0.97,
            "duration_from_previous_seconds": 30.61
        },
        {
            "path": "2019\\2019-06-17_末代皇帝_影评",
            "end_time": "2025-08-26 15:36:13",
            "size_bytes": 1229215,
            "size_mb": 1.17,
            "duration_from_previous_seconds": 27.67
        },
        {
            "path": "2019\\2019-06-16_作为过来人，我告诉你  别过来",
            "end_time": "2025-08-26 15:36:47",
            "size_bytes": 2516964,
            "size_mb": 2.4,
            "duration_from_previous_seconds": 33.38
        },
        {
            "path": "2019\\2019-06-06_朝花夕拾，组图扫街",
            "end_time": "2025-08-26 15:37:39",
            "size_bytes": 2782125,
            "size_mb": 2.65,
            "duration_from_previous_seconds": 51.85
        },
        {
            "path": "2019\\2019-05-31_送毕业后的碎碎念",
            "end_time": "2025-08-26 15:38:01",
            "size_bytes": 672067,
            "size_mb": 0.64,
            "duration_from_previous_seconds": 22.73
        },
        {
            "path": "2019\\2019-05-28_一点迷惑行为观察",
            "end_time": "2025-08-26 15:38:27",
            "size_bytes": 1744191,
            "size_mb": 1.66,
            "duration_from_previous_seconds": 26.16
        },
        {
            "path": "2019\\2019-05-23_我们重视坎本身，更甚于坎的意义",
            "end_time": "2025-08-26 15:39:12",
            "size_bytes": 284146,
            "size_mb": 0.27,
            "duration_from_previous_seconds": 44.64
        },
        {
            "path": "2019\\2019-05-18_紫菘停水停电停网前后24小时",
            "end_time": "2025-08-26 15:39:39",
            "size_bytes": 1143005,
            "size_mb": 1.09,
            "duration_from_previous_seconds": 27.28
        },
        {
            "path": "2019\\2019-05-16_豆浆和摘抄本",
            "end_time": "2025-08-26 15:40:05",
            "size_bytes": 328214,
            "size_mb": 0.31,
            "duration_from_previous_seconds": 25.21
        },
        {
            "path": "2019\\2019-05-13_第十三周周一的早课和白日梦",
            "end_time": "2025-08-26 15:40:22",
            "size_bytes": 255238,
            "size_mb": 0.24,
            "duration_from_previous_seconds": 17.72
        },
        {
            "path": "2019\\2019-05-12_连续加班十九天之后",
            "end_time": "2025-08-26 15:40:47",
            "size_bytes": 940695,
            "size_mb": 0.9,
            "duration_from_previous_seconds": 24.93
        },
        {
            "path": "2019\\2019-05-01_衔瑜，这里补交七篇读后感",
            "end_time": "2025-08-26 15:41:11",
            "size_bytes": 611554,
            "size_mb": 0.58,
            "duration_from_previous_seconds": 23.58
        },
        {
            "path": "2019\\2019-04-28_命运这辆公交车，我没有座位",
            "end_time": "2025-08-26 15:41:39",
            "size_bytes": 1654605,
            "size_mb": 1.58,
            "duration_from_previous_seconds": 28.54
        },
        {
            "path": "2019\\2019-04-23_报复性熬夜·暴食·随笔",
            "end_time": "2025-08-26 15:42:07",
            "size_bytes": 520540,
            "size_mb": 0.5,
            "duration_from_previous_seconds": 28.03
        },
        {
            "path": "2019\\2019-04-21_暴戾的标准化流程",
            "end_time": "2025-08-26 15:42:33",
            "size_bytes": 831843,
            "size_mb": 0.79,
            "duration_from_previous_seconds": 25.53
        },
        {
            "path": "2019\\2019-04-15_留下尬走的足迹_深圳",
            "end_time": "2025-08-26 15:43:19",
            "size_bytes": 1824466,
            "size_mb": 1.74,
            "duration_from_previous_seconds": 46.47
        },
        {
            "path": "2019\\2019-04-03_私奔，在武昌汉口的生活里",
            "end_time": "2025-08-26 15:44:34",
            "size_bytes": 3099700,
            "size_mb": 2.96,
            "duration_from_previous_seconds": 74.29
        },
        {
            "path": "2019\\2019-03-31_如果没有这碗肠粉，今天不过又是个普通的周末",
            "end_time": "2025-08-26 15:45:03",
            "size_bytes": 1174430,
            "size_mb": 1.12,
            "duration_from_previous_seconds": 29.39
        },
        {
            "path": "2019\\2019-03-29_别说跳出舒适圈，现在的问题是没有舒适圈",
            "end_time": "2025-08-26 15:45:25",
            "size_bytes": 475009,
            "size_mb": 0.45,
            "duration_from_previous_seconds": 21.51
        },
        {
            "path": "2019\\2019-03-27_“对抗焦虑”是如何被制造出来的？",
            "end_time": "2025-08-26 15:45:51",
            "size_bytes": 917194,
            "size_mb": 0.87,
            "duration_from_previous_seconds": 26.04
        },
        {
            "path": "2019\\2019-03-25_生活应该怎样继续",
            "end_time": "2025-08-26 15:46:17",
            "size_bytes": 754891,
            "size_mb": 0.72,
            "duration_from_previous_seconds": 26.65
        },
        {
            "path": "2019\\2019-03-04_追着光梦游_一周图集",
            "end_time": "2025-08-26 15:47:05",
            "size_bytes": 3353129,
            "size_mb": 3.2,
            "duration_from_previous_seconds": 47.86
        },
        {
            "path": "2019\\2019-02-24_戏，是这样多吗？",
            "end_time": "2025-08-26 15:47:53",
            "size_bytes": 1118299,
            "size_mb": 1.07,
            "duration_from_previous_seconds": 47.59
        },
        {
            "path": "2019\\2019-02-11_当代戏精文学与沙雕图研究",
            "end_time": "2025-08-26 15:48:38",
            "size_bytes": 1692346,
            "size_mb": 1.61,
            "duration_from_previous_seconds": 44.95
        },
        {
            "path": "2019\\2019-02-07_为什么还要继续做现在在做的事呢",
            "end_time": "2025-08-26 15:49:01",
            "size_bytes": 796441,
            "size_mb": 0.76,
            "duration_from_previous_seconds": 23.31
        },
        {
            "path": "2019\\2019-02-02_长沙人是检验臭豆腐的唯一标准",
            "end_time": "2025-08-26 15:51:03",
            "size_bytes": 14203900,
            "size_mb": 13.55,
            "duration_from_previous_seconds": 122.22
        },
        {
            "path": "2019\\2019-01-26_留下尬走的足迹_合肥",
            "end_time": "2025-08-26 15:52:08",
            "size_bytes": 2657694,
            "size_mb": 2.53,
            "duration_from_previous_seconds": 64.72
        },
        {
            "path": "2019\\2019-01-20_留下尬走的足迹_长春",
            "end_time": "2025-08-26 15:52:46",
            "size_bytes": 2489715,
            "size_mb": 2.37,
            "duration_from_previous_seconds": 37.62
        },
        {
            "path": "2019\\2019-01-15_未写完的不具名",
            "end_time": "2025-08-26 15:53:51",
            "size_bytes": 4663626,
            "size_mb": 4.45,
            "duration_from_previous_seconds": 65.63
        },
        {
            "path": "2019\\2019-01-12_我吃外卖披萨的时候一定要看成龙历险记（点头",
            "end_time": "2025-08-26 15:54:26",
            "size_bytes": 1735793,
            "size_mb": 1.66,
            "duration_from_previous_seconds": 34.46
        },
        {
            "path": "2019\\2019-01-06_失焦的注意力",
            "end_time": "2025-08-26 15:54:47",
            "size_bytes": 500619,
            "size_mb": 0.48,
            "duration_from_previous_seconds": 21.81
        },
        {
            "path": "2018\\2018-12-31_总是容易被往事打动_100图和衔瑜的2018再见",
            "end_time": "2025-08-26 15:57:12",
            "size_bytes": 12987302,
            "size_mb": 12.39,
            "duration_from_previous_seconds": 144.43
        },
        {
            "path": "2018\\2018-12-24_恋爱要不要苟延残喘？",
            "end_time": "2025-08-26 15:57:58",
            "size_bytes": 3178836,
            "size_mb": 3.03,
            "duration_from_previous_seconds": 46.58
        },
        {
            "path": "2018\\2018-12-22_修正秩序当中那些不万能的部分",
            "end_time": "2025-08-26 15:58:28",
            "size_bytes": 1152079,
            "size_mb": 1.1,
            "duration_from_previous_seconds": 29.76
        },
        {
            "path": "2018\\2018-12-21_我今作力所能及的解说",
            "end_time": "2025-08-26 15:59:21",
            "size_bytes": 416229,
            "size_mb": 0.4,
            "duration_from_previous_seconds": 53.16
        },
        {
            "path": "2018\\2018-12-12_汉阳火车站_一枚武汉的古旧印章",
            "end_time": "2025-08-26 15:59:52",
            "size_bytes": 1634301,
            "size_mb": 1.56,
            "duration_from_previous_seconds": 30.21
        },
        {
            "path": "2018\\2018-12-02_和郁结坐下来谈妥一次",
            "end_time": "2025-08-26 16:00:12",
            "size_bytes": 409666,
            "size_mb": 0.39,
            "duration_from_previous_seconds": 20.52
        },
        {
            "path": "2018\\2018-11-30_鲁磨路有在过马路",
            "end_time": "2025-08-26 16:00:35",
            "size_bytes": 495211,
            "size_mb": 0.47,
            "duration_from_previous_seconds": 22.84
        },
        {
            "path": "2018\\2018-11-21_关于光谷我知道的不多",
            "end_time": "2025-08-26 16:01:00",
            "size_bytes": 707535,
            "size_mb": 0.67,
            "duration_from_previous_seconds": 25.47
        },
        {
            "path": "2018\\2018-10-31_重拾《倚天屠龙记》后的随笔",
            "end_time": "2025-08-26 16:01:16",
            "size_bytes": 164100,
            "size_mb": 0.16,
            "duration_from_previous_seconds": 15.49
        },
        {
            "path": "2018\\2018-10-07_留下尬走的足迹_新加坡",
            "end_time": "2025-08-26 16:02:35",
            "size_bytes": 4784800,
            "size_mb": 4.56,
            "duration_from_previous_seconds": 78.98
        },
        {
            "path": "2018\\2018-09-12_湘江水逝楚云飞 _ 域见",
            "end_time": "2025-08-26 16:03:27",
            "size_bytes": 1180264,
            "size_mb": 1.13,
            "duration_from_previous_seconds": 51.83
        },
        {
            "path": "2018\\2018-09-05_你是一支聚酯，好久没有再回来过。",
            "end_time": "2025-08-26 16:03:49",
            "size_bytes": 289984,
            "size_mb": 0.28,
            "duration_from_previous_seconds": 22.69
        },
        {
            "path": "2018\\2018-08-25_如果用脑内来看最近新闻中的问题，那我就有了两组问题",
            "end_time": "2025-08-26 16:04:13",
            "size_bytes": 249401,
            "size_mb": 0.24,
            "duration_from_previous_seconds": 23.41
        },
        {
            "path": "2018\\2018-08-12_留下尬走的足迹_北京",
            "end_time": "2025-08-26 16:04:53",
            "size_bytes": 3525316,
            "size_mb": 3.36,
            "duration_from_previous_seconds": 39.78
        },
        {
            "path": "2018\\2018-08-09_朴素思路的若干重载",
            "end_time": "2025-08-26 16:05:19",
            "size_bytes": 557679,
            "size_mb": 0.53,
            "duration_from_previous_seconds": 26.63
        },
        {
            "path": "2018\\2018-07-31_文不加点的张衔瑜有一岁了",
            "end_time": "2025-08-26 16:05:48",
            "size_bytes": 590921,
            "size_mb": 0.56,
            "duration_from_previous_seconds": 29.19
        },
        {
            "path": "2018\\2018-07-16_我在北京 因为药神而多走了两步",
            "end_time": "2025-08-26 16:06:19",
            "size_bytes": 1387049,
            "size_mb": 1.32,
            "duration_from_previous_seconds": 30.69
        },
        {
            "path": "2018\\2018-07-10_无病呻吟",
            "end_time": "2025-08-26 16:06:43",
            "size_bytes": 199922,
            "size_mb": 0.19,
            "duration_from_previous_seconds": 23.95
        },
        {
            "path": "2018\\2018-07-08_明明说了话 别人却不明白",
            "end_time": "2025-08-26 16:07:31",
            "size_bytes": 255966,
            "size_mb": 0.24,
            "duration_from_previous_seconds": 47.57
        },
        {
            "path": "2018\\2018-06-30_我是张衔瑜 我回来了啦",
            "end_time": "2025-08-26 16:07:58",
            "size_bytes": 258928,
            "size_mb": 0.25,
            "duration_from_previous_seconds": 26.92
        },
        {
            "path": "2018\\2018-05-28_留下尬走的足迹_再到上海",
            "end_time": "2025-08-26 16:08:28",
            "size_bytes": 675378,
            "size_mb": 0.64,
            "duration_from_previous_seconds": 30.26
        },
        {
            "path": "2018\\2018-05-18_拨乱反正赠送的语肝",
            "end_time": "2025-08-26 16:08:55",
            "size_bytes": 382057,
            "size_mb": 0.36,
            "duration_from_previous_seconds": 27.16
        },
        {
            "path": "2018\\2018-05-04_有道理&&没有价值",
            "end_time": "2025-08-26 16:09:23",
            "size_bytes": 1138210,
            "size_mb": 1.09,
            "duration_from_previous_seconds": 27.92
        },
        {
            "path": "2018\\2018-05-03_清醒与清醒的泥沼",
            "end_time": "2025-08-26 16:09:46",
            "size_bytes": 274500,
            "size_mb": 0.26,
            "duration_from_previous_seconds": 23.05
        },
        {
            "path": "2018\\2018-04-13_几个最近的小波动",
            "end_time": "2025-08-26 16:10:12",
            "size_bytes": 282310,
            "size_mb": 0.27,
            "duration_from_previous_seconds": 26.01
        },
        {
            "path": "2018\\2018-04-02_斐波那契的日程表",
            "end_time": "2025-08-26 16:11:03",
            "size_bytes": 278750,
            "size_mb": 0.27,
            "duration_from_previous_seconds": 50.56
        },
        {
            "path": "2018\\2018-03-14_下笔太狠的雨声 拈花杀了诗人",
            "end_time": "2025-08-26 16:11:27",
            "size_bytes": 269466,
            "size_mb": 0.26,
            "duration_from_previous_seconds": 23.97
        },
        {
            "path": "2018\\2018-03-01_只是不想取一个《深夜文摘》那样的题目",
            "end_time": "2025-08-26 16:11:52",
            "size_bytes": 145972,
            "size_mb": 0.14,
            "duration_from_previous_seconds": 25.66
        },
        {
            "path": "2018\\2018-02-17_衔瑜过年不被吃的办法",
            "end_time": "2025-08-26 16:12:21",
            "size_bytes": 324641,
            "size_mb": 0.31,
            "duration_from_previous_seconds": 28.64
        },
        {
            "path": "2018\\2018-02-13_如果你愿意一层一层地剥开这层茧",
            "end_time": "2025-08-26 16:12:48",
            "size_bytes": 370830,
            "size_mb": 0.35,
            "duration_from_previous_seconds": 27.62
        },
        {
            "path": "2018\\2018-02-11_一撮热卤一撮湘",
            "end_time": "2025-08-26 16:13:17",
            "size_bytes": 391637,
            "size_mb": 0.37,
            "duration_from_previous_seconds": 28.74
        },
        {
            "path": "2018\\2018-02-06_舆论常常是私刑 私刑常常是娱乐",
            "end_time": "2025-08-26 16:14:07",
            "size_bytes": 190462,
            "size_mb": 0.18,
            "duration_from_previous_seconds": 50.07
        },
        {
            "path": "2018\\2018-02-05_科研二三事",
            "end_time": "2025-08-26 16:14:36",
            "size_bytes": 523833,
            "size_mb": 0.5,
            "duration_from_previous_seconds": 28.86
        },
        {
            "path": "2018\\2018-01-31_姗姗来迟的『茶颜悦色_知乎茶也』测评",
            "end_time": "2025-08-26 16:15:14",
            "size_bytes": 780527,
            "size_mb": 0.74,
            "duration_from_previous_seconds": 38.16
        },
        {
            "path": "2018\\2018-01-31_今天我助力了天朝的老龄化进程",
            "end_time": "2025-08-26 16:15:37",
            "size_bytes": 144723,
            "size_mb": 0.14,
            "duration_from_previous_seconds": 22.92
        },
        {
            "path": "2018\\2018-01-22_只是尽可能的简单 却不再简化",
            "end_time": "2025-08-26 16:16:05",
            "size_bytes": 485759,
            "size_mb": 0.46,
            "duration_from_previous_seconds": 27.47
        },
        {
            "path": "2018\\2018-01-20_今晚看话剧回来 心里像憋着一壶叫喊",
            "end_time": "2025-08-26 16:16:31",
            "size_bytes": 185050,
            "size_mb": 0.18,
            "duration_from_previous_seconds": 26.35
        },
        {
            "path": "2018\\2018-01-19_回归·失踪人口·张衔瑜",
            "end_time": "2025-08-26 16:17:15",
            "size_bytes": 484143,
            "size_mb": 0.46,
            "duration_from_previous_seconds": 44.22
        },
        {
            "path": "2018\\2018-01-13_写在大物草稿纸上的小说",
            "end_time": "2025-08-26 16:18:06",
            "size_bytes": 157054,
            "size_mb": 0.15,
            "duration_from_previous_seconds": 50.6
        },
        {
            "path": "2018\\2018-01-06_舍友都出门了的时候",
            "end_time": "2025-08-26 16:18:33",
            "size_bytes": 271488,
            "size_mb": 0.26,
            "duration_from_previous_seconds": 27.45
        },
        {
            "path": "2018\\2018-01-05_日子就很平常",
            "end_time": "2025-08-26 16:19:00",
            "size_bytes": 1330818,
            "size_mb": 1.27,
            "duration_from_previous_seconds": 27.01
        },
        {
            "path": "2018\\2018-01-01_今天这一篇是凑数的",
            "end_time": "2025-08-26 16:19:31",
            "size_bytes": 326310,
            "size_mb": 0.31,
            "duration_from_previous_seconds": 30.36
        },
        {
            "path": "2017\\2017-12-28_这是你的羁绊",
            "end_time": "2025-08-26 16:20:06",
            "size_bytes": 357080,
            "size_mb": 0.34,
            "duration_from_previous_seconds": 35.35
        },
        {
            "path": "2017\\2017-12-25_君子之交肝若醴",
            "end_time": "2025-08-26 16:20:55",
            "size_bytes": 416318,
            "size_mb": 0.4,
            "duration_from_previous_seconds": 48.94
        },
        {
            "path": "2017\\2017-12-23_苦尽肝来",
            "end_time": "2025-08-26 16:21:19",
            "size_bytes": 541060,
            "size_mb": 0.52,
            "duration_from_previous_seconds": 24.5
        },
        {
            "path": "2017\\2017-12-15_今天读篇鲁迅 说点有的没的",
            "end_time": "2025-08-26 16:21:39",
            "size_bytes": 128562,
            "size_mb": 0.12,
            "duration_from_previous_seconds": 19.73
        },
        {
            "path": "2017\\2017-11-30_别到了长沙 还不知道怎么嗦粉",
            "end_time": "2025-08-26 16:59:12",
            "size_bytes": 540790,
            "size_mb": 0.52,
            "duration_from_previous_seconds": 2253.11
        },
        {
            "path": "2017\\2017-11-21_猜猜我今天要说什么",
            "end_time": "2025-08-26 16:59:24",
            "size_bytes": 969439,
            "size_mb": 0.92,
            "duration_from_previous_seconds": 11.55
        },
        {
            "path": "2017\\2017-11-16_雅礼，今天我为你写下小札",
            "end_time": "2025-08-26 16:59:41",
            "size_bytes": 1499114,
            "size_mb": 1.43,
            "duration_from_previous_seconds": 16.87
        },
        {
            "path": "2017\\2017-11-11_在不安的世界里 安静地活着",
            "end_time": "2025-08-26 16:59:57",
            "size_bytes": 273743,
            "size_mb": 0.26,
            "duration_from_previous_seconds": 15.96
        },
        {
            "path": "2017\\2017-11-10_今年双十一也没点长进吗",
            "end_time": "2025-08-26 17:00:36",
            "size_bytes": 1637481,
            "size_mb": 1.56,
            "duration_from_previous_seconds": 39.1
        },
        {
            "path": "2017\\2017-11-08_无以言表的集体感",
            "end_time": "2025-08-26 17:01:10",
            "size_bytes": 1810273,
            "size_mb": 1.73,
            "duration_from_previous_seconds": 34.16
        },
        {
            "path": "2017\\2017-11-02_11.02 听说这样play tricks的都脱团了",
            "end_time": "2025-08-26 17:01:26",
            "size_bytes": 213277,
            "size_mb": 0.2,
            "duration_from_previous_seconds": 15.67
        },
        {
            "path": "2017\\2017-10-29_在油腻的生活中诗意地栖居",
            "end_time": "2025-08-26 17:02:04",
            "size_bytes": 1020809,
            "size_mb": 0.97,
            "duration_from_previous_seconds": 38.52
        },
        {
            "path": "2017\\2017-10-21_想讨论点关于教育的事",
            "end_time": "2025-08-26 17:02:21",
            "size_bytes": 393505,
            "size_mb": 0.38,
            "duration_from_previous_seconds": 16.7
        },
        {
            "path": "2017\\2017-10-06_几件小事",
            "end_time": "2025-08-26 17:02:42",
            "size_bytes": 2349247,
            "size_mb": 2.24,
            "duration_from_previous_seconds": 20.87
        },
        {
            "path": "2017\\2017-10-05_从狼人杀看《李尔王》",
            "end_time": "2025-08-26 17:02:55",
            "size_bytes": 219063,
            "size_mb": 0.21,
            "duration_from_previous_seconds": 13.72
        },
        {
            "path": "2017\\2017-10-02_化学生的求生攻略",
            "end_time": "2025-08-26 17:03:30",
            "size_bytes": 2496750,
            "size_mb": 2.38,
            "duration_from_previous_seconds": 34.48
        },
        {
            "path": "2017\\2017-09-24_一周之内  而气候不齐",
            "end_time": "2025-08-26 17:03:50",
            "size_bytes": 476129,
            "size_mb": 0.45,
            "duration_from_previous_seconds": 20.51
        },
        {
            "path": "2017\\2017-09-21_奶茶要不啦~奶茶",
            "end_time": "2025-08-26 17:04:36",
            "size_bytes": 595079,
            "size_mb": 0.57,
            "duration_from_previous_seconds": 45.13
        },
        {
            "path": "2017\\2017-09-17_子龙一身都是胆 我一身都是肝",
            "end_time": "2025-08-26 17:05:05",
            "size_bytes": 302672,
            "size_mb": 0.29,
            "duration_from_previous_seconds": 29.53
        },
        {
            "path": "2017\\2017-09-01_留下的尬走足迹_香港",
            "end_time": "2025-08-26 17:06:42",
            "size_bytes": 4509726,
            "size_mb": 4.3,
            "duration_from_previous_seconds": 96.85
        },
        {
            "path": "2017\\2017-08-25_留下的尬走足迹_大连",
            "end_time": "2025-08-26 17:07:47",
            "size_bytes": 1546439,
            "size_mb": 1.47,
            "duration_from_previous_seconds": 65.04
        },
        {
            "path": "2017\\2017-08-23_留下尬走的足迹_上海",
            "end_time": "2025-08-26 17:08:21",
            "size_bytes": 1567959,
            "size_mb": 1.5,
            "duration_from_previous_seconds": 33.74
        },
        {
            "path": "2017\\2017-08-22_留下尬走的足迹_苏州",
            "end_time": "2025-08-26 17:08:57",
            "size_bytes": 1794532,
            "size_mb": 1.71,
            "duration_from_previous_seconds": 36.71
        },
        {
            "path": "2017\\2017-08-20_留下尬走的足迹_杭州",
            "end_time": "2025-08-26 17:09:23",
            "size_bytes": 1225160,
            "size_mb": 1.17,
            "duration_from_previous_seconds": 25.2
        },
        {
            "path": "2017\\2017-08-11_杂感",
            "end_time": "2025-08-26 17:09:37",
            "size_bytes": 922824,
            "size_mb": 0.88,
            "duration_from_previous_seconds": 14.16
        },
        {
            "path": "2017\\2017-08-08_公号写了一周了  可是人设还没有出来",
            "end_time": "2025-08-26 17:09:54",
            "size_bytes": 305194,
            "size_mb": 0.29,
            "duration_from_previous_seconds": 16.87
        },
        {
            "path": "2017\\2017-08-06_衔瑜脑洞_五条衔瑜 鱼目混珠",
            "end_time": "2025-08-26 17:10:19",
            "size_bytes": 351274,
            "size_mb": 0.34,
            "duration_from_previous_seconds": 25.12
        },
        {
            "path": "2017\\2017-08-04_衔瑜训诂_说尬",
            "end_time": "2025-08-26 17:10:42",
            "size_bytes": 393980,
            "size_mb": 0.38,
            "duration_from_previous_seconds": 23.48
        },
        {
            "path": "2017\\2017-08-03_衔瑜文艺_好久不见",
            "end_time": "2025-08-26 17:10:57",
            "size_bytes": 183950,
            "size_mb": 0.18,
            "duration_from_previous_seconds": 14.65
        },
        {
            "path": "2017\\2017-08-02_衔瑜攻略_2017.08.02",
            "end_time": "2025-08-26 17:11:21",
            "size_bytes": 728165,
            "size_mb": 0.69,
            "duration_from_previous_seconds": 24.18
        },
        {
            "path": "2017\\2017-08-01_衔瑜小札_2017.07.31",
            "end_time": "2025-08-26 17:11:43",
            "size_bytes": 709749,
            "size_mb": 0.68,
            "duration_from_previous_seconds": 21.82
        },
        {
            "path": "2017\\2017-07-31_破蛋推_衔瑜今天成年啦！！！",
            "end_time": "2025-08-26 17:12:13",
            "size_bytes": 683399,
            "size_mb": 0.65,
            "duration_from_previous_seconds": 30.14
        }
    ],
    "yearly_summary": {
        "2025": {
            "total_size_bytes": 94200456,
            "total_download_duration_seconds": 1019.1571760000002
        },
        "2024": {
            "total_size_bytes": 376964550,
            "total_download_duration_seconds": 2595.148236
        },
        "2023": {
            "total_size_bytes": 86256214,
            "total_download_duration_seconds": 1377.5311490000001
        },
        "2022": {
            "total_size_bytes": 155556585,
            "total_download_duration_seconds": 1758.0715229999998
        },
        "2021": {
            "total_size_bytes": 140052109,
            "total_download_duration_seconds": 1899.5358319999998
        },
        "2020": {
            "total_size_bytes": 315780595,
            "total_download_duration_seconds": 4494.071462999999
        },
        "2019": {
            "total_size_bytes": 105168626,
            "total_download_duration_seconds": 2306.440356
        },
        "2018": {
            "total_size_bytes": 43839407,
            "total_download_duration_seconds": 1483.1910659999996
        },
        "2017": {
            "total_size_bytes": 31162742,
            "total_download_duration_seconds": 3162.368325
        }
    }
}